ftimecache/__init__.py
ftimecache/ftimecache.py
timecache/__init__.py
timecache/timecache.py
ftimecache-0.0.2.dist-info/METADATA
ftimecache-0.0.2.dist-info/WHEEL
ftimecache-0.0.2.dist-info/top_level.txt
ftimecache-0.0.2.dist-info/RECORD
