Metadata-Version: 2.1
Name: ftimecache
Version: 0.0.2
Summary: Decorator to cache function return values based on time.
Home-page: https://github.com/Dimfred/ftimecache
Author: dimfred
Author-email: dimfred.1337@web.de
License: MIT
Platform: UNKNOWN
Classifier: Programming Language :: Python :: 3.7
Classifier: Programming Language :: Python :: 3.10
Classifier: Programming Language :: Python :: 3.9
Classifier: Programming Language :: Python :: 3
Classifier: Programming Language :: Python :: 3.8
